ucwa_sdk/__init__.py
ucwa_sdk/client.py
ucwa_sdk/config.py
ucwa_sdk/execption.py
ucwa_sdk/memory.py
ucwa_sdk/model.py
ucwa_sdk/utils.py
ucwa_sdk-1.0.0.dist-info/METADATA
ucwa_sdk-1.0.0.dist-info/WHEEL
ucwa_sdk-1.0.0.dist-info/top_level.txt
ucwa_sdk-1.0.0.dist-info/RECORD
